pocketcoder/__init__.py
pocketcoder/__main__.py
pocketcoder/requirements.txt
pocketcoder/config/__init__.py
pocketcoder/config/settings.py
pocketcoder/core/__init__.py
pocketcoder/core/applier.py
pocketcoder/core/coder.py
pocketcoder/core/condense.py
pocketcoder/core/content_preview.py
pocketcoder/core/episodes.py
pocketcoder/core/models.py
pocketcoder/core/parser.py
pocketcoder/core/project_context.py
pocketcoder/core/prompt_loader.py
pocketcoder/core/repo_map.py
pocketcoder/core/session.py
pocketcoder/core/summary.py
pocketcoder/core/memory/__init__.py
pocketcoder/core/memory/chat_storage.py
pocketcoder/core/memory/classifier.py
pocketcoder/core/memory/extractor.py
pocketcoder/core/memory/manager.py
pocketcoder/core/memory/storage.py
pocketcoder/core/memory/types.py
pocketcoder/core/prompts/base.txt
pocketcoder/core/prompts/tools_compact.txt
pocketcoder/core/prompts/tools_full.json
pocketcoder/core/prompts/fewshot/agent.txt
pocketcoder/core/prompts/fewshot/creative.txt
pocketcoder/core/prompts/fewshot/debug.txt
pocketcoder/core/prompts/fewshot/edit.txt
pocketcoder/core/prompts/fewshot/file.txt
pocketcoder/core/prompts/fewshot/git.txt
pocketcoder/core/prompts/fewshot/memory.txt
pocketcoder/core/prompts/fewshot/shell.txt
pocketcoder/core/prompts/os/linux.txt
pocketcoder/core/prompts/os/macos.txt
pocketcoder/core/prompts/os/windows.txt
pocketcoder/hooks/__init__.py
pocketcoder/hooks/manager.py
pocketcoder/prompts/system/code_editor.yaml
pocketcoder/providers/__init__.py
pocketcoder/providers/anthropic.py
pocketcoder/providers/base.py
pocketcoder/providers/ollama.py
pocketcoder/providers/openai.py
pocketcoder/providers/openai_compat.py
pocketcoder/repomap/__init__.py
pocketcoder/repomap/simple.py
pocketcoder/tools/__init__.py
pocketcoder/tools/agent.py
pocketcoder/tools/edit.py
pocketcoder/tools/files.py
pocketcoder/tools/history.py
pocketcoder/tools/shell.py
pocketcoder/ui/__init__.py
pocketcoder/ui/cli.py
pocketcoder/ui/feedback.py
pocketcoder/ui/formatters.py
pocketcoder-1.0.3.dist-info/METADATA
pocketcoder-1.0.3.dist-info/WHEEL
pocketcoder-1.0.3.dist-info/entry_points.txt
pocketcoder-1.0.3.dist-info/licenses/LICENSE
pocketcoder-1.0.3.dist-info/RECORD
