Metadata-Version: 2.4
Name: pocketcoder
Version: 1.0.3
Summary: AI-powered coding assistant optimized for local LLMs
Project-URL: Homepage, https://github.com/Chashchin-Dmitry/pocketcoder
Project-URL: Documentation, https://github.com/Chashchin-Dmitry/pocketcoder#readme
Project-URL: Repository, https://github.com/Chashchin-Dmitry/pocketcoder
Author: PocketCoder Team
License-Expression: MIT
License-File: LICENSE
Keywords: ai,assistant,coding,llm,ollama
Classifier: Development Status :: 4 - Beta
Classifier: Intended Audience :: Developers
Classifier: License :: OSI Approved :: MIT License
Classifier: Programming Language :: Python :: 3
Classifier: Programming Language :: Python :: 3.8
Classifier: Programming Language :: Python :: 3.9
Classifier: Programming Language :: Python :: 3.10
Classifier: Programming Language :: Python :: 3.11
Classifier: Programming Language :: Python :: 3.12
Requires-Python: >=3.8
Requires-Dist: click>=8.1.0
Requires-Dist: jinja2>=3.1.0
Requires-Dist: prompt-toolkit>=3.0.0
Requires-Dist: pyyaml>=6.0.0
Requires-Dist: requests>=2.31.0
Requires-Dist: rich>=13.0.0
Provides-Extra: all
Requires-Dist: black>=23.0.0; extra == 'all'
Requires-Dist: gradio>=4.0.0; extra == 'all'
Requires-Dist: mypy>=1.7.0; extra == 'all'
Requires-Dist: pytest-cov>=4.1.0; extra == 'all'
Requires-Dist: pytest>=7.4.0; extra == 'all'
Requires-Dist: responses>=0.24.0; extra == 'all'
Requires-Dist: ruff>=0.1.0; extra == 'all'
Requires-Dist: tree-sitter-javascript>=0.21.0; extra == 'all'
Requires-Dist: tree-sitter-python>=0.21.0; extra == 'all'
Requires-Dist: tree-sitter>=0.21.0; extra == 'all'
Provides-Extra: dev
Requires-Dist: black>=23.0.0; extra == 'dev'
Requires-Dist: mypy>=1.7.0; extra == 'dev'
Requires-Dist: pytest-cov>=4.1.0; extra == 'dev'
Requires-Dist: pytest>=7.4.0; extra == 'dev'
Requires-Dist: responses>=0.24.0; extra == 'dev'
Requires-Dist: ruff>=0.1.0; extra == 'dev'
Provides-Extra: treesitter
Requires-Dist: tree-sitter-javascript>=0.21.0; extra == 'treesitter'
Requires-Dist: tree-sitter-python>=0.21.0; extra == 'treesitter'
Requires-Dist: tree-sitter>=0.21.0; extra == 'treesitter'
Provides-Extra: web
Requires-Dist: gradio>=4.0.0; extra == 'web'
